awk_dataframe/__init__.py
awk_dataframe/awk_dataframe.py
awk_dataframe/read_file_direct_output.cpp
awk_dataframe/write_to_file.cpp
awk_dataframe/bin/linux/parse_complex_csv
awk_dataframe/bin/linux/save_csv
awk_dataframe-0.2.12.dist-info/LICENSE
awk_dataframe-0.2.12.dist-info/METADATA
awk_dataframe-0.2.12.dist-info/WHEEL
awk_dataframe-0.2.12.dist-info/top_level.txt
awk_dataframe-0.2.12.dist-info/RECORD
