Metadata-Version: 2.1
Name: awk-dataframe
Version: 0.2.12
Summary: Wrapper around awk to use as a dataframe implementation in python
Home-page: UNKNOWN
Author: Carlos Molinero
Author-email: 
License: MIT
Platform: UNKNOWN
Classifier: Programming Language :: Python :: 3
Classifier: Operating System :: OS Independent
License-File: LICENSE
